indexedlines.py
openfile.py
indexedlines-0.1.0.dist-info/DESCRIPTION.rst
indexedlines-0.1.0.dist-info/METADATA
indexedlines-0.1.0.dist-info/RECORD
indexedlines-0.1.0.dist-info/WHEEL
indexedlines-0.1.0.dist-info/metadata.json
indexedlines-0.1.0.dist-info/top_level.txt
