Metadata-Version: 2.0
Name: indexedlines
Version: 0.1.0
Summary: A convenience list-like object that allows random access tolines of a text file.
Home-page: https://github.com/luismsgomes/indexedlines
Author: Luís Gomes
Author-email: luismsgomes@gmail.com
License: MIT
Keywords: convenience
Platform: UNKNOWN
Classifier: Development Status :: 3 - Alpha
Classifier: License :: OSI Approved :: MIT License
Classifier: Programming Language :: Python :: 3.5
Requires-Dist: openfile
